LICENSE
MANIFEST.in
README.md
setup.py
pyawad/__init__.py
pyawad/request.py
pyawad/util.py
pyawad.egg-info/PKG-INFO
pyawad.egg-info/SOURCES.txt
pyawad.egg-info/dependency_links.txt
pyawad.egg-info/requires.txt
pyawad.egg-info/top_level.txt