Metadata-Version: 1.1
Name: pyawad
Version: 0.0.2
Summary: Anywayanyday API python wrapper
Home-page: https://github.com/netstuff/pyawad
Author: Yuri Andreev Jr.
Author-email: andreev.jr@gmail.com
License: MIT
Download-URL: https://github.com/netstuff/pyawad/archive/master.zip
Keywords: anywayanyday api aiohttp
Platform: UNKNOWN
Classifier: Environment :: Web Environment
Classifier: Intended Audience :: Developers
Classifier: Programming Language :: Python
